fast_hpack/__init__.py
fast_hpack/hpack.py
fast_hpack/huffman.py
fast_hpack/table.py
fast_hpack-0.1.0.dist-info/LICENSE
fast_hpack-0.1.0.dist-info/METADATA
fast_hpack-0.1.0.dist-info/WHEEL
fast_hpack-0.1.0.dist-info/top_level.txt
fast_hpack-0.1.0.dist-info/RECORD
